{
    "/js/app.js": "/js/app.js",
    "/css/app.css": "/css/app.css",
    "/web/css/blog.list.css": "/web/css/blog.list.css",
    "/web/css/bootstrap-responsive.css": "/web/css/bootstrap-responsive.css",
    "/web/css/bootstrap-responsive.min.css": "/web/css/bootstrap-responsive.min.css",
    "/web/css/bootstrap.css": "/web/css/bootstrap.css",
    "/web/css/bootstrap.min.css": "/web/css/bootstrap.min.css",
    "/web/css/flexslider.css": "/web/css/flexslider.css",
    "/web/css/font-awesome-ie7.css": "/web/css/font-awesome-ie7.css",
    "/web/css/font-awesome.css": "/web/css/font-awesome.css",
    "/web/css/fontastic.css": "/web/css/fontastic.css",
    "/web/css/overwrite.css": "/web/css/overwrite.css",
    "/web/css/prettyPhoto.css": "/web/css/prettyPhoto.css",
    "/web/css/style.default.css": "/web/css/style.default.css",
    "/web/js/app.js": "/web/js/app.js",
    "/web/js/bootstrap.js": "/web/js/bootstrap.js",
    "/web/js/bootstrap.min.js": "/web/js/bootstrap.min.js",
    "/web/js/contactform.js": "/web/js/contactform.js",
    "/web/js/custom.js": "/web/js/custom.js",
    "/web/js/front.js": "/web/js/front.js",
    "/web/js/inview.js": "/web/js/inview.js",
    "/web/js/isotope.js": "/web/js/isotope.js",
    "/web/js/jquery-3.2.1.min.js": "/web/js/jquery-3.2.1.min.js",
    "/web/js/jquery-hover-effect.js": "/web/js/jquery-hover-effect.js",
    "/web/js/jquery.flexslider.js": "/web/js/jquery.flexslider.js",
    "/web/js/jquery.js": "/web/js/jquery.js",
    "/web/js/jquery.localScroll.js": "/web/js/jquery.localScroll.js",
    "/web/js/jquery.nav.js": "/web/js/jquery.nav.js",
    "/web/js/jquery.prettyPhoto.js": "/web/js/jquery.prettyPhoto.js",
    "/web/js/jquery.scrollTo.js": "/web/js/jquery.scrollTo.js",
    "/web/js/popper.min.js": "/web/js/popper.min.js",
    "/admin/css/app-test.css": "/admin/css/app-test.css",
    "/admin/css/app.css": "/admin/css/app.css",
    "/admin/css/bootstrap-datepicker.min.css": "/admin/css/bootstrap-datepicker.min.css",
    "/admin/css/bootstrap-tagsinput.css": "/admin/css/bootstrap-tagsinput.css",
    "/admin/css/bootstrap.min.css": "/admin/css/bootstrap.min.css",
    "/admin/css/bootstrap3-wysihtml5.min.css": "/admin/css/bootstrap3-wysihtml5.min.css",
    "/admin/css/daterangepicker.css": "/admin/css/daterangepicker.css",
    "/admin/css/font-awesome.min.css": "/admin/css/font-awesome.min.css",
    "/admin/css/font-google.css": "/admin/css/font-google.css",
    "/admin/css/ionicons.min.css": "/admin/css/ionicons.min.css",
    "/admin/css/jquery-jvectormap.css": "/admin/css/jquery-jvectormap.css",
    "/admin/css/local.css": "/admin/css/local.css",
    "/admin/css/morris.css": "/admin/css/morris.css",
    "/admin/css/select2.min.css": "/admin/css/select2.min.css",
    "/admin/css/style-login.css": "/admin/css/style-login.css",
    "/admin/js/app.js": "/admin/js/app.js",
    "/admin/js/bootstrap-datepicker.min.js": "/admin/js/bootstrap-datepicker.min.js",
    "/admin/js/bootstrap-tagsinput.js": "/admin/js/bootstrap-tagsinput.js",
    "/admin/js/bootstrap.min.js": "/admin/js/bootstrap.min.js",
    "/admin/js/bootstrap3-wysihtml5.all.min.js": "/admin/js/bootstrap3-wysihtml5.all.min.js",
    "/admin/js/dataTables.bootstrap.min.js": "/admin/js/dataTables.bootstrap.min.js",
    "/admin/js/daterangepicker.js": "/admin/js/daterangepicker.js",
    "/admin/js/fastclick.js": "/admin/js/fastclick.js",
    "/admin/js/icheck.min.js": "/admin/js/icheck.min.js",
    "/admin/js/jquery-jvectormap-1.2.2.min.js": "/admin/js/jquery-jvectormap-1.2.2.min.js",
    "/admin/js/jquery-jvectormap-world-mill-en.js": "/admin/js/jquery-jvectormap-world-mill-en.js",
    "/admin/js/jquery-ui.min.js": "/admin/js/jquery-ui.min.js",
    "/admin/js/jquery.dataTables.min.js": "/admin/js/jquery.dataTables.min.js",
    "/admin/js/jquery.flot.categories.js": "/admin/js/jquery.flot.categories.js",
    "/admin/js/jquery.flot.js": "/admin/js/jquery.flot.js",
    "/admin/js/jquery.flot.pie.js": "/admin/js/jquery.flot.pie.js",
    "/admin/js/jquery.flot.resize.js": "/admin/js/jquery.flot.resize.js",
    "/admin/js/jquery.flot.time.js": "/admin/js/jquery.flot.time.js",
    "/admin/js/jquery.inputmask.date.extensions.js": "/admin/js/jquery.inputmask.date.extensions.js",
    "/admin/js/jquery.inputmask.extensions.js": "/admin/js/jquery.inputmask.extensions.js",
    "/admin/js/jquery.inputmask.js": "/admin/js/jquery.inputmask.js",
    "/admin/js/jquery.inputmask.numeric.extensions.js": "/admin/js/jquery.inputmask.numeric.extensions.js",
    "/admin/js/jquery.inputmask.phone.extensions.js": "/admin/js/jquery.inputmask.phone.extensions.js",
    "/admin/js/jquery.inputmask.regex.extensions.js": "/admin/js/jquery.inputmask.regex.extensions.js",
    "/admin/js/jquery.knob.min.js": "/admin/js/jquery.knob.min.js",
    "/admin/js/jquery.min.js": "/admin/js/jquery.min.js",
    "/admin/js/jquery.slimscroll.min.js": "/admin/js/jquery.slimscroll.min.js",
    "/admin/js/jquery.sparkline.min.js": "/admin/js/jquery.sparkline.min.js",
    "/admin/js/jquery.validate.min.js": "/admin/js/jquery.validate.min.js",
    "/admin/js/js-login.js": "/admin/js/js-login.js",
    "/admin/js/moment.min.js": "/admin/js/moment.min.js",
    "/admin/js/morris.min.js": "/admin/js/morris.min.js",
    "/admin/js/raphael.min.js": "/admin/js/raphael.min.js",
    "/admin/js/select2.full.min.js": "/admin/js/select2.full.min.js",
    "/admin/js/utilities/common.js": "/admin/js/utilities/common.js",
    "/admin/js/utilities/form.validate.js": "/admin/js/utilities/form.validate.js",
    "/admin/js/utilities/jquery.validate.messages.js": "/admin/js/utilities/jquery.validate.messages.js",
    "/admin/js/utilities/scroll.bar.js": "/admin/js/utilities/scroll.bar.js"
}
